{
   "name": "pg_repack",
   "abstract": "PostgreSQL module for data reorganization",
   "description": "Reorganize tables in PostgreSQL databases with minimal locks",
   "version": "1.4.0",
   "maintainer": [
       "Josh Kupershmidt <schmiddy@gmail.com>",
       "Daniele Varrazzo <daniele.varrazzo@gmail.com>",
       "Beena Emerson <memissemerson@gmail.com>"
    ],
   "tags": [ "bloat", "maintenance", "vacuum", "cluster" ],
   "release_status": "stable",
   "license": "bsd",
   "provides": {
      "pg_repack": {
         "file": "lib/pg_repack.sql",
         "version": "1.4.0",
         "abstract": "Reorganize tables in PostgreSQL databases with minimal locks"
      }
   },
   "prereqs": {
      "runtime": {
         "requires": {
            "PostgreSQL": "8.3.0"
         }
      }
   },
   "resources": {
      "homepage": "http://reorg.github.com/pg_repack",
      "bugtracker": {
         "web": "https://github.com/reorg/pg_repack/issues"
      },
      "repository": {
          "url": "git://github.com/reorg/pg_repack.git",
          "web": "https://github.com/reorg/pg_repack/",
          "type": "git"
      }
   },
   "meta-spec": {
      "version": "1.0.0",
      "url": "http://pgxn.org/meta/spec.txt"
   }
}
